main.py
pdf_injector-0.1.1.dist-info/METADATA
pdf_injector-0.1.1.dist-info/WHEEL
pdf_injector-0.1.1.dist-info/entry_points.txt
pdf_injector-0.1.1.dist-info/top_level.txt
pdf_injector-0.1.1.dist-info/RECORD
