Metadata-Version: 2.4
Name: pdf-injector
Version: 0.1.1
Summary: Tool for injecting invisible text into PDFs
Requires-Python: >=3.12
Requires-Dist: pypdf>=3.0.0
Requires-Dist: reportlab>=4.0.0
Provides-Extra: dev
Requires-Dist: pytest>=7.0.0; extra == "dev"
Requires-Dist: pyright>=1.1.0; extra == "dev"
Requires-Dist: ruff>=0.1.0; extra == "dev"
